.coveragerc
.gitignore
.travis.yml
CONTRIBUTING.md
LICENSE
MANIFEST.in
README.md
requirements.txt
setup.py
docs/Makefile
docs/make.bat
docs/source/conf.py
docs/source/configuration.rst
docs/source/contributing.rst
docs/source/index.rst
docs/source/install.rst
docs/source/intro.rst
docs/source/modules.rst
docs/source/options.rst
docs/source/pyiso.rst
docs/source/supporting.rst
docs/source/usage.rst
pyiso/__init__.py
pyiso/aeso.py
pyiso/base.py
pyiso/bchydro.py
pyiso/bpa.py
pyiso/caiso.py
pyiso/eia_esod.py
pyiso/ercot.py
pyiso/eu.py
pyiso/ieso.py
pyiso/isone.py
pyiso/miso.py
pyiso/nbpower.py
pyiso/nlhydro.py
pyiso/nspower.py
pyiso/nvenergy.py
pyiso/nyiso.py
pyiso/pei.py
pyiso/pjm.py
pyiso/sask.py
pyiso/spp.py
pyiso/sveri.py
pyiso/tasks.py
pyiso/yukon.py
pyiso.egg-info/PKG-INFO
pyiso.egg-info/SOURCES.txt
pyiso.egg-info/dependency_links.txt
pyiso.egg-info/requires.txt
pyiso.egg-info/top_level.txt
responses/20160401rtfuelmix.csv.zip
responses/20160517_da_ex.xls
responses/AZPS_1-4.txt
responses/AZPS_1-4_latest.txt
responses/AZPS_5-8.txt
responses/AZPS_5-8_latest.txt
responses/DEAA_1-4.txt
responses/DEAA_1-4_latest.txt
responses/DEAA_5-8.txt
responses/DEAA_5-8_latest.txt
responses/ELE_1-4.txt
responses/ELE_1-4_latest.txt
responses/ELE_5-8.txt
responses/ELE_5-8_latest.txt
responses/ENE_SLRS.zip
responses/GRIF_1-4.txt
responses/GRIF_1-4_latest.txt
responses/GRIF_5-8.txt
responses/GRIF_5-8_latest.txt
responses/HGMA_1-4.txt
responses/HGMA_1-4_latest.txt
responses/HGMA_5-8.txt
responses/HGMA_5-8_latest.txt
responses/IID_1-4.txt
responses/IID_1-4_latest.txt
responses/IID_5-8.txt
responses/IID_5-8_latest.txt
responses/NEVP_load_farpast.htm
responses/PNM_1-4.txt
responses/PNM_1-4_latest.txt
responses/PNM_5-8.txt
responses/PNM_5-8_latest.txt
responses/SLD_FCST.zip
responses/SLD_REN_FCST.zip
responses/SPPC_load_farpast.htm
responses/SRP_1-4.txt
responses/SRP_1-4_latest.txt
responses/SRP_5-8.txt
responses/SRP_5-8_latest.txt
responses/TEPC_1-4.txt
responses/TEPC_1-4_latest.txt
responses/TEPC_5-8.txt
responses/TEPC_5-8_latest.txt
responses/WALC_1-4.txt
responses/WALC_1-4_latest.txt
responses/WALC_5-8.txt
